<Defs>

	<!-- this def is used to create various sanity gain/loss effects. other mods can create their own defs or patch this def to add their sanity gains/losses for various things -->
	<VAEInsanity.SanityEffectsDef>
		<defName>VAEI_SanityEffects</defName>
		<psychicRitualEffects>
			<li>
				<ritual>VoidProvocation</ritual>
				<invokerEffect>-0.01</invokerEffect>
			</li>
			<li>
				<ritual>SummonAnimals</ritual>
				<invokerEffect>-0.01</invokerEffect>
			</li>
			<li>
				<ritual>SummonShamblers</ritual>
				<invokerEffect>-0.02</invokerEffect>
				<chanterEffect>-0.005</chanterEffect>
			</li>
			<li>
				<ritual>Chronophagy</ritual>
				<invokerEffect>-0.05</invokerEffect>
				<chanterEffect>-0.005</chanterEffect>
				<targetEffect>-0.01</targetEffect>
			</li>
			<li>
				<ritual>Psychophagy</ritual>
				<invokerEffect>-0.05</invokerEffect>
				<chanterEffect>-0.01</chanterEffect>
				<targetEffect>-0.01</targetEffect>
			</li>
			<li>
				<ritual>SkipAbduction</ritual>
				<invokerEffect>-0.03</invokerEffect>
				<chanterEffect>-0.02</chanterEffect>
			</li>
			<li>
				<ritual>SummonFleshbeasts</ritual>
				<invokerEffect>-0.02</invokerEffect>
				<chanterEffect>-0.005</chanterEffect>
			</li>
			<li>
				<ritual>SummonPitGate</ritual>
				<invokerEffect>-0.03</invokerEffect>
				<chanterEffect>-0.005</chanterEffect>
			</li>
			<li>
				<ritual>ImbueDeathRefusal</ritual>
				<invokerEffect>-0.03</invokerEffect>
				<chanterEffect>-0.005</chanterEffect>
				<targetEffect>-0.08</targetEffect>
			</li>
			<li>
				<ritual>Philophagy</ritual>
				<invokerEffect>-0.05</invokerEffect>
			</li>
			<li>
				<ritual>PleasurePulse</ritual>
				<invokerEffect>-0.01</invokerEffect>
			</li>
			<li>
				<ritual>NeurosisPulse</ritual>
				<invokerEffect>-0.02</invokerEffect>
			</li>
			<li>
				<ritual>BloodRain</ritual>
				<invokerEffect>-0.03</invokerEffect>
				<chanterEffect>-0.01</chanterEffect>
			</li>
			<li>
				<ritual>Brainwipe</ritual>
				<invokerEffect>-0.08</invokerEffect>
			</li>
		</psychicRitualEffects>
		<disturbingInitiatorEffects><!-- when the initiator is disturbing, recipient will get following sanity effects -->
			<li>
				<interaction>Chitchat</interaction>
				<effect>-0.01</effect>
			</li>
			<li>
				<interaction>DeepTalk</interaction>
				<effect>-0.02</effect>
			</li>
			<li>
				<interaction>KindWords</interaction>
				<effect>-0.03</effect>
			</li>
			<li>
				<interaction>Nuzzle</interaction>
				<effect>-0.02</effect>
			</li>
			<li>
				<interaction>RomanceAttempt</interaction>
				<effect>-0.05</effect>
			</li>
			<li>
				<interaction>MarriageProposal</interaction>
				<effect>-0.05</effect>
			</li>
			<li MayRequire="Ludeon.RimWorld.Biotech">
				<interaction>BabyPlay</interaction>
				<effect>-0.04</effect>
			</li>
			<li MayRequire="Ludeon.RimWorld.Ideology">
				<interaction>Counsel_Success</interaction>
				<effect>-0.05</effect>
			</li>
			<li MayRequire="Ludeon.RimWorld.Ideology">
				<interaction>Reassure</interaction>
				<effect>-0.05</effect>
			</li>
			<li MayRequire="VanillaExpanded.VanillaSocialInteractionsExpanded">
				<interaction>VSIE_Vent</interaction>
				<effect>-0.03</effect>
			</li>
			<li MayRequire="OskarPotocki.VFE.Empire">
				<interaction>VFEE_RoyalGossip</interaction>
				<effect>-0.01</effect>
			</li>
		</disturbingInitiatorEffects>
		<interactionEffects>
			<li>
				<interaction>CreepyWords</interaction>
				<effect>-0.025</effect>
			</li>
			<li>
				<interaction>DisturbingChat</interaction>
				<effect>-0.025</effect>
			</li>
			<li>
				<interaction>OccultTeaching</interaction>
				<effect>-0.005</effect>
			</li>
			<li>
				<interaction>VAEI_TwistedWords</interaction>
				<effect>-0.025</effect>
			</li>
			<li>
				<interaction>VAEI_UnsettlingTalk</interaction>
				<effect>-0.03</effect>
			</li>
		</interactionEffects>
		<nonDisturbingInitiatorEffects>
			<li>
				<interaction>Chitchat</interaction>
				<effect>0.01</effect>
			</li>
			<li>
				<interaction>DeepTalk</interaction>
				<effect>0.02</effect>
			</li>
			<li>
				<interaction>KindWords</interaction>
				<effect>0.03</effect>
			</li>
			<li>
				<interaction>Nuzzle</interaction>
				<effect>0.02</effect>
			</li>
			<li>
				<interaction>RomanceAttempt</interaction>
				<effect>0.05</effect>
			</li>
			<li>
				<interaction>MarriageProposal</interaction>
				<effect>0.05</effect>
			</li>
			<li MayRequire="Ludeon.RimWorld.Biotech">
				<interaction>BabyPlay</interaction>
				<effect>0.04</effect>
			</li>
			<li MayRequire="Ludeon.RimWorld.Ideology">
				<interaction>Counsel_Success</interaction>
				<effect>0.05</effect>
			</li>
			<li MayRequire="Ludeon.RimWorld.Ideology">
				<interaction>Reassure</interaction>
				<effect>0.05</effect>
			</li>
			<li MayRequire="VanillaExpanded.VanillaSocialInteractionsExpanded">
				<interaction>VSIE_Vent</interaction>
				<effect>0.03</effect>
			</li>
			<li MayRequire="OskarPotocki.VFE.Empire">
				<interaction>VFEE_RoyalGossip</interaction>
				<effect>0.01</effect>
			</li>
		</nonDisturbingInitiatorEffects>
		<hediffEffects>
			<li>
				<hediff>FleshmassLung</hediff>
				<effect>-0.004</effect>
			</li>
			<li>
				<hediff>FleshmassStomach</hediff>
				<effect>-0.004</effect>
			</li>
			<li>
				<hediff>FleshWhip</hediff>
				<effect>-0.004</effect>
			</li>
			<li>
				<hediff>Tentacle</hediff>
				<effect>-0.004</effect>
			</li>
			<li>
				<hediff>CubeInterest</hediff>
				<effect>-0.005</effect>
				<description>Cube interest</description>
			</li>
			<li>
				<hediff>CubeWithdrawal</hediff>
				<effect>-0.01</effect>
				<description>Cube withdrawal</description>
			</li>
		</hediffEffects>
		<usedThingsEffects>
			<li>
				<thing>Apparel_ShardPsychicShockLance</thing>
				<effect>-0.01</effect>
			</li>
			<li>
				<thing>Apparel_ShardPsychicInsanityLance</thing>
				<effect>-0.01</effect>
			</li>
			<li>
				<thing>Apparel_BiomutationLance</thing>
				<effect>-0.01</effect>
			</li>
			<li>
				<thing>VoidsightSerum</thing>
				<effect>-0.005</effect>
			</li>
			<li>
				<thing>MetalbloodSerum</thing>
				<effect>-0.005</effect>
			</li>
			<li>
				<thing>MindNumbSerum</thing>
				<effect>-0.005</effect>
			</li>
		</usedThingsEffects>
		<killedThingsEffects>
			<li>
				<thing>Bulbfreak</thing>
				<effect>0.01</effect>
			</li>
			<li>
				<thing>Toughspike</thing>
				<effect>0.004</effect>
			</li>
			<li>
				<thing>Trispike</thing>
				<effect>0.004</effect>
			</li>
			<li>
				<thing>Fingerspike</thing>
				<effect>0.002</effect>
			</li>
			<li>
				<thing>Dreadmeld</thing>
				<effect>0.05</effect>
			</li>
			<li>
				<thing>Sightstealer</thing>
				<effect>0.005</effect>
			</li>
			<li>
				<thing>Revenant</thing>
				<effect>0.03</effect>
			</li>
			<li>
				<thing>Metalhorror</thing>
				<effect>0.05</effect>
			</li>
			<li>
				<thing>Noctol</thing>
				<effect>0.03</effect>
			</li>
		</killedThingsEffects>
		<ritualEffects>
			<li MayRequire="Ludeon.RimWorld.Royalty">
				<ritual>AttendedSpeech</ritual>
				<effect>0.0~0.01</effect>
			</li>
			<li MayRequire="Ludeon.RimWorld.Royalty">
				<ritual>AnimaTreeLinking</ritual>
				<effect>0.0~0.01</effect>
			</li>
			<li MayRequire="Ludeon.RimWorld.Ideology">
				<ritual>AttendedFuneral</ritual>
				<effect>0.0~0.02</effect>
			</li>
			<li MayRequire="Ludeon.RimWorld.Ideology">
				<ritual>AttendedFuneralNoCorpse</ritual>
				<effect>0.0~0.02</effect>
			</li>

			<li MayRequire="Ludeon.RimWorld.Ideology">
				<ritual>CelebrationPartyDanceTech</ritual>
				<effect>0.0~0.02</effect>
			</li>
			<li MayRequire="Ludeon.RimWorld.Ideology">
				<ritual>CelebrationPartyDanceDrum</ritual>
				<effect>0.0~0.02</effect>
			</li>
			<li MayRequire="Ludeon.RimWorld.Ideology">
				<ritual>CelebrationSkyLanterns</ritual>
				<effect>0.0~0.02</effect>
			</li>
			<li MayRequire="Ludeon.RimWorld.Ideology">
				<ritual>DestroyConsumableBuilding_ChristmasTree</ritual>
				<effect>0.0~0.02</effect>
			</li>
			<li MayRequire="Ludeon.RimWorld.Ideology">
				<ritual>CelebratedDate</ritual>
				<effect>0.0~0.02</effect>
			</li>
			<li MayRequire="Ludeon.RimWorld.Ideology">
				<ritual>ConnectToTree</ritual>
				<effect>0.0~0.01</effect>
			</li>
			<li MayRequire="Ludeon.RimWorld.Biotech">
				<ritual>ChildBirth</ritual>
				<effect>0.0~0.05</effect>
			</li>
			<li MayRequire="OskarPotocki.VFE.Empire">
				<ritual>VFEE_RoyalAddres_Outcome</ritual>
				<effect>0.0~0.02</effect>
			</li>
			<li MayRequire="OskarPotocki.VFE.Empire">
				<ritual>VFEE_GrandBall_Outcome</ritual>
				<effect>0.0~0.01</effect>
			</li>
		</ritualEffects>
		<rehumanizationTraits>
			<li>VAEI_Germaphobe</li>
			<li>VAEI_Noncommittal</li>
			<li>VAEI_Unstable</li>
			<li>VAEI_Distractable</li>
			<li>VAEI_MoodSwings</li>
		</rehumanizationTraits>
	</VAEInsanity.SanityEffectsDef>

</Defs>